cfo/__init__.py
cfo/__version__.py
cfo/utils.py
cfo/data/paths.json
cfo-1.0.1.dist-info/LICENSE
cfo-1.0.1.dist-info/METADATA
cfo-1.0.1.dist-info/WHEEL
cfo-1.0.1.dist-info/top_level.txt
cfo-1.0.1.dist-info/RECORD
