Metadata-Version: 2.1
Name: cfo
Version: 1.0.1
Summary: Python wrappers for accessing Forest Observatory data via the Salo API
Home-page: https://github.com/forestobservatory/cfo-api
Author: Salo Sciences
Author-email: cba@salo.ai
License: MIT
Keywords: ecology,conservation,remote sensing,wildfire,california
Platform: any
Classifier: Programming Language :: Python :: 3
Classifier: License :: OSI Approved :: MIT License
Classifier: Operating System :: OS Independent
Requires-Python: >=3.0
Requires-Dist: requests
Requires-Dist: retrying
